{
    "version": "1.15.3",
    "description": "Small self-contained pure-Go web server with Lua, Markdown, HTTP/2, QUIC, Redis and PostgreSQL support",
    "homepage": "https://algernon.roboticoverlords.org",
    "license": "MIT",
    "architecture": {
        "64bit": {
            "url": "https://github.com/xyproto/algernon/releases/download/v1.15.3/algernon-1.15.3-windows_x86_64_static.zip",
            "hash": "c3342f42d4dfdb85c5c284227bc1668e14ea5e013f85c1f23b7bc83de8d7eb88",
            "extract_dir": "algernon-1.15.3-windows_x86_64_static"
        }
    },
    "bin": "algernon.exe",
    "checkver": {
        "github": "https://github.com/xyproto/algernon"
    },
    "autoupdate": {
        "architecture": {
            "64bit": {
                "url": "https://github.com/xyproto/algernon/releases/download/v$version/algernon-$version-windows_x86_64_static.zip",
                "extract_dir": "algernon-$version-windows_x86_64_static"
            }
        }
    }
}
