{
    "version": "3.46.0",
    "description": "A file list program that supports multiple storage, powered by Gin and Solidjs.",
    "homepage": "https://alist.nn.ci",
    "license": "AGPL-3.0-or-later",
    "architecture": {
        "64bit": {
            "url": "https://github.com/alist-org/alist/releases/download/v3.46.0/alist-windows-amd64.zip",
            "hash": "md5:50962f14d6bcd29653edc8892cf7d2ae"
        },
        "32bit": {
            "url": "https://github.com/alist-org/alist/releases/download/v3.46.0/alist-windows-386.zip",
            "hash": "md5:a977537370d333ce5cc85affa820ad25"
        },
        "arm64": {
            "url": "https://github.com/alist-org/alist/releases/download/v3.46.0/alist-windows-arm64.zip",
            "hash": "md5:84e019e0b3aecb95df6636feb1498136"
        }
    },
    "bin": [
        [
            "alist.exe",
            "alist",
            "--force-bin-dir"
        ]
    ],
    "persist": [
        "data",
        "log"
    ],
    "checkver": {
        "github": "https://github.com/alist-org/alist"
    },
    "autoupdate": {
        "architecture": {
            "64bit": {
                "url": "https://github.com/alist-org/alist/releases/download/v$version/alist-windows-amd64.zip"
            },
            "32bit": {
                "url": "https://github.com/alist-org/alist/releases/download/v$version/alist-windows-386.zip"
            },
            "arm64": {
                "url": "https://github.com/alist-org/alist/releases/download/v$version/alist-windows-arm64.zip"
            }
        },
        "hash": {
            "url": "$baseurl/md5.txt"
        }
    }
}
