{
    "version": "1.8.0",
    "license": "MIT",
    "url": "https://github.com/lihaoyi/Ammonite/releases/download/1.8.0/2.12-1.8.0#/amm.bat",
    "bin": "amm.bat",
    "homepage": "http://ammonite.io",
    "description": "Ammonite lets you use the Scala language for scripting purposes: in the REPL, as scripts, as a library, or as a standalone systems shell.",
    "hash": "45da027b0312af019d6a3a6e0fe43a16e96794261a0e518c96bd536d27cf5eb3",
    "checkver": {
        "github": "https://github.com/lihaoyi/Ammonite"
    },
    "autoupdate": {
        "url": "https://github.com/lihaoyi/Ammonite/releases/download/$version/2.12-$version#/amm.bat"
    },
    "suggest": {
        "JDK": [
            "java/oraclejdk",
            "java/openjdk"
        ]
    }
}
