{
    "version": "17.1.4",
    "description": "Official balena CLI for interacting with balenaCloud and balena API.",
    "homepage": "https://github.com/balena-io/balena-cli",
    "license": "Apache-2.0",
    "architecture": {
        "64bit": {
            "url": "https://github.com/balena-io/balena-cli/releases/download/v17.1.4/balena-cli-v17.1.4-windows-x64-standalone.zip",
            "hash": "723ddcc5fd6f3d0d71e784017ce2165a1a95f72326af0ab47b829fad91c0442e"
        }
    },
    "extract_dir": "balena-cli",
    "bin": "balena.exe",
    "checkver": "github",
    "autoupdate": {
        "architecture": {
            "64bit": {
                "url": "https://github.com/balena-io/balena-cli/releases/download/v$version/balena-cli-v$version-windows-x64-standalone.zip"
            }
        }
    }
}
