{
    "version": "22.4.13",
    "description": "Official balena CLI for interacting with balenaCloud and balena API.",
    "homepage": "https://github.com/balena-io/balena-cli",
    "license": "Apache-2.0",
    "architecture": {
        "64bit": {
            "url": "https://github.com/balena-io/balena-cli/releases/download/v22.4.13/balena-cli-v22.4.13-windows-x64-standalone.tar.gz",
            "hash": "ff33923f823d258a009a9d9263cbe301a912f831ad9d84fe955eccb4fa4633f9"
        }
    },
    "extract_dir": "balena",
    "bin": "bin/balena.cmd",
    "checkver": "github",
    "autoupdate": {
        "architecture": {
            "64bit": {
                "url": "https://github.com/balena-io/balena-cli/releases/download/v$version/balena-cli-v$version-windows-x64-standalone.tar.gz"
            }
        }
    }
}
