{
    "version": "12.51.0",
    "description": "Official balena CLI for interacting with balenaCloud and balena API.",
    "homepage": "https://github.com/balena-io/balena-cli",
    "license": "Apache-2.0",
    "architecture": {
        "64bit": {
            "url": "https://github.com/balena-io/balena-cli/releases/download/v12.51.0/balena-cli-v12.51.0-windows-x64-standalone.zip",
            "hash": "12147a8c6cf5ef111538ec9e9d2fa4233f24ec86de4cca1ed4b1ccc52cdad0ef"
        }
    },
    "extract_dir": "balena-cli",
    "bin": "balena.exe",
    "checkver": "github",
    "autoupdate": {
        "architecture": {
            "64bit": {
                "url": "https://github.com/balena-io/balena-cli/releases/download/v$version/balena-cli-v$version-windows-x64-standalone.zip"
            }
        }
    }
}
