{
    "version": "1.20.2",
    "description": "The Crystal Programming Language",
    "homepage": "https://www.crystal-lang.org/",
    "license": "Apache-2.0",
    "architecture": {
        "64bit": {
            "url": "https://github.com/crystal-lang/crystal/releases/download/1.20.2/crystal-1.20.2-windows-x86_64-msvc-unsupported.zip",
            "hash": "15a41963373cc481f68dcc9a968bb11d36ee9254f1515eccee86d02223f8f82e"
        }
    },
    "bin": [
        "crystal.exe",
        "shards.exe"
    ],
    "shortcuts": [
        [
            "crystal.exe",
            "Crystal",
            "i"
        ]
    ],
    "checkver": {
        "github": "https://github.com/crystal-lang/crystal",
        "jsonpath": "$..browser_download_url",
        "regex": "crystal-(?<version>[\\d.-]+)-windows-x86_64"
    },
    "autoupdate": {
        "architecture": {
            "64bit": {
                "url": "https://github.com/crystal-lang/crystal/releases/download/$matchHead/crystal-$version-windows-x86_64-msvc-unsupported.zip"
            }
        }
    }
}
