{
    "version": "1.6.0",
    "description": "A secure runtime for JavaScript and TypeScript",
    "homepage": "https://deno.land",
    "license": "MIT",
    "architecture": {
        "64bit": {
            "url": "https://github.com/denoland/deno/releases/download/v1.6.0/deno-x86_64-pc-windows-msvc.zip",
            "hash": "ad570b68fc06fde9be165127ec4174bcfb8587f99410410fbd4c61fb971fba05"
        }
    },
    "bin": "deno.exe",
    "checkver": {
        "github": "https://github.com/denoland/deno"
    },
    "autoupdate": {
        "architecture": {
            "64bit": {
                "url": "https://github.com/denoland/deno/releases/download/v$version/deno-x86_64-pc-windows-msvc.zip"
            }
        }
    }
}
