{
    "version": "146.0.3856.78",
    "description": "Close the loop on your developer cycle by automating testing of your website in Microsoft Edge (Chromium).",
    "homepage": "https://developer.microsoft.com/en-us/microsoft-edge/tools/webdriver",
    "license": {
        "identifier": "Freeware",
        "url": "https://msedgedriver.microsoft.com/EULA"
    },
    "notes": "For legacy (EdgeHTML) version, see 'versions/edgedriver-legacy'.",
    "architecture": {
        "64bit": {
            "url": "https://msedgedriver.microsoft.com/146.0.3856.78/edgedriver_win64.zip",
            "hash": "96aca7364a625742c5a3d33688bf67e8d18b458ea26020f67005693567bfc97a"
        },
        "32bit": {
            "url": "https://msedgedriver.microsoft.com/146.0.3856.78/edgedriver_win32.zip",
            "hash": "8854a628249d02c8f110b347a87691427accc795cd83d3ccc8b3842eec90bd91"
        },
        "arm64": {
            "url": "https://msedgedriver.microsoft.com/146.0.3856.78/edgedriver_arm64.zip",
            "hash": "1a8d28d6ff124fe7061eb3a4a1fafc84e25fc347dea836acf2c2dbad4cc4303b"
        }
    },
    "bin": "msedgedriver.exe",
    "checkver": {
        "script": "Write-Output $([System.Text.Encoding]::Unicode.GetString((Invoke-WebRequest -URI https://msedgedriver.microsoft.com/LATEST_STABLE).Content))",
        "regex": "([\\d.]+)"
    },
    "autoupdate": {
        "architecture": {
            "64bit": {
                "url": "https://msedgedriver.microsoft.com/$version/edgedriver_win64.zip"
            },
            "32bit": {
                "url": "https://msedgedriver.microsoft.com/$version/edgedriver_win32.zip"
            },
            "arm64": {
                "url": "https://msedgedriver.microsoft.com/$version/edgedriver_arm64.zip"
            }
        }
    }
}
