{
    "version": "3.27.0",
    "description": "Ferium is a CLI Minecraft mod manager for mods from Modrinth, CurseForge, and Github Releases.",
    "homepage": "https://github.com/theRookieCoder/ferium",
    "license": "MPL-2.0",
    "architecture": {
        "64bit": {
                "url": "https://github.com/theRookieCoder/ferium/releases/download/v3.27.0/ferium-windows-msvc.zip",
                "hash": "83e9d861077ec15f5d700bfc81b20e77f58df24d9f1538210a98b4667a238517"
            }
    },
    "bin": "ferium.exe",
    "checkver": "github",
    "autoupdate": {
        "architecture": {
            "64bit": {
                "url": "https://github.com/theRookieCoder/ferium/releases/download/v$version/ferium-windows-msvc.zip"
            }
        },
        "hash": "https://github.com/theRookieCoder/ferium/releases/download/v$version/ferium-windows-msvc.zip.sha256"
    }
}