{
    "version": "103470",
    "description": "A complete, cross-platform solution to record, convert and stream audio and video.",
    "homepage": "https://ffmpeg.org",
    "license": "GPL-3.0-or-later",
    "architecture": {
        "64bit": {
            "url": "https://github.com/BtbN/FFmpeg-Builds/releases/download/autobuild-2021-09-01-12-22/ffmpeg-N-103470-gc500dc7cca-win64-gpl.zip",
            "hash": "202931b25a05dbeffe3386791bf4fe5a6d70b479f7274337d6334ac78da45ba9",
            "extract_dir": "ffmpeg-N-103470-gc500dc7cca-win64-gpl"
        }
    },
    "bin": [
        "bin\\ffmpeg.exe",
        "bin\\ffplay.exe",
        "bin\\ffprobe.exe"
    ],
    "checkver": {
        "github": "https://github.com/BtbN/FFmpeg-Builds",
        "regex": "/autobuild-(?<time>[\\d-]+)/ffmpeg-N-(?<version>\\d+)-g(?<hash>[a-z\\d]+)-win64-gpl\\.zip"
    },
    "autoupdate": {
        "architecture": {
            "64bit": {
                "url": "https://github.com/BtbN/FFmpeg-Builds/releases/download/autobuild-$matchTime/ffmpeg-N-$version-g$matchHash-win64-gpl.zip",
                "extract_dir": "ffmpeg-N-$version-g$matchHash-win64-gpl"
            }
        }
    }
}
