{
    "version": "100131",
    "description": "A complete, cross-platform solution to record, convert and stream audio and video.",
    "homepage": "https://ffmpeg.org",
    "license": "GPL-3.0-or-later",
    "architecture": {
        "64bit": {
            "url": "https://github.com/BtbN/FFmpeg-Builds/releases/download/autobuild-2020-12-03-12-54/ffmpeg-N-100131-g0639f5c294-win64-gpl-shared.zip",
            "hash": "7b200d7334ef4f4db90930e43c2df6fbac3f27d6ea5b4be1862ea49a9ca8d3f6",
            "extract_dir": "ffmpeg-N-100131-g0639f5c294-win64-gpl-shared"
        }
    },
    "bin": [
        "bin\\ffmpeg.exe",
        "bin\\ffplay.exe",
        "bin\\ffprobe.exe"
    ],
    "checkver": {
        "github": "https://github.com/BtbN/FFmpeg-Builds",
        "regex": "/autobuild-(?<time>[\\d-]+)/ffmpeg-N-(\\d+)-g(?<hash>[a-z\\d]+)-win64-gpl-shared\\.zip"
    },
    "autoupdate": {
        "architecture": {
            "64bit": {
                "url": "https://github.com/BtbN/FFmpeg-Builds/releases/download/autobuild-$matchTime/ffmpeg-N-$version-g$matchHash-win64-gpl-shared.zip",
                "extract_dir": "ffmpeg-N-$version-g$matchHash-win64-gpl-shared"
            }
        }
    }
}
