{
    "version": "0.219.5",
    "description": "A static type checker for JavaScript code",
    "homepage": "https://flowtype.org/",
    "license": "MIT",
    "architecture": {
        "64bit": {
            "url": "https://github.com/facebook/flow/releases/download/v0.219.5/flow-win64-v0.219.5.zip",
            "hash": "328bb88eaec920dd84243b333d3cc36bf8c144a075596c27909c16d61c13fcf5"
        }
    },
    "extract_dir": "flow",
    "bin": "flow.exe",
    "checkver": {
        "github": "https://github.com/facebook/flow"
    },
    "autoupdate": {
        "architecture": {
            "64bit": {
                "url": "https://github.com/facebook/flow/releases/download/v$version/flow-win64-v$version.zip"
            }
        }
    }
}
