{
    "version": "0.3.119",
    "description": "Command line deployment/management client for fly.io services",
    "homepage": "https://github.com/superfly/flyctl",
    "license": " Apache-2.0",
    "architecture": {
        "64bit": {
            "url": "https://github.com/superfly/flyctl/releases/download/v0.3.119/flyctl_0.3.119_Windows_x86_64.zip",
            "hash": "2fc7f63eaa2aab89a49d9763357f942f14464c4d295cc988e295e8e8bcd0674d"
        },
        "arm64": {
            "url": "https://github.com/superfly/flyctl/releases/download/v0.3.119/flyctl_0.3.119_Windows_arm64.zip",
            "hash": "1aa74b81b4e52ec3938be04ccd1afcfe5b083ad7c31513de2582f350328036bf"
        }
    },
    "bin": [
        "flyctl.exe",
        [
            "flyctl.exe",
            "fly"
        ]
    ],
    "checkver": "github",
    "autoupdate": {
        "architecture": {
            "64bit": {
                "url": "https://github.com/superfly/flyctl/releases/download/v$version/flyctl_$version_Windows_x86_64.zip"
            },
            "arm64": {
                "url": "https://github.com/superfly/flyctl/releases/download/v$version/flyctl_$version_Windows_arm64.zip"
            }
        },
        "hash": {
            "url": "$baseurl/checksums.txt"
        }
    }
}
