{
    "version": "1.51.2",
    "description": "Lightweight, portable and dependable accounting tools",
    "homepage": "https://hledger.org",
    "license": "GPL-3.0-only",
    "architecture": {
        "64bit": {
            "url": "https://github.com/simonmichael/hledger/releases/download/1.51.2/hledger-windows-x64.zip",
            "hash": "10b7da22a2893065159fcb28325cced05c63d745e20b48e26ecfa9e9b8f711f0"
        }
    },
    "bin": [
        "hledger.exe",
        "hledger-web.exe",
        "hledger-ui.exe"
    ],
    "checkver": {
        "github": "https://github.com/simonmichael/hledger"
    },
    "autoupdate": {
        "architecture": {
            "64bit": {
                "url": "https://github.com/simonmichael/hledger/releases/download/$version/hledger-windows-x64.zip"
            }
        }
    }
}
