{
    "version": "0.163.0",
    "description": "Speedy and flexible static site generator (without Sass/SCSS support)",
    "homepage": "https://gohugo.io",
    "license": "Apache-2.0",
    "architecture": {
        "64bit": {
            "url": "https://github.com/gohugoio/hugo/releases/download/v0.163.0/hugo_0.163.0_windows-amd64.zip",
            "hash": "c86a67e9709ea3bbeb1e88b66ce06250892e6ca3cbc08c39c20ac2b51639938f"
        },
        "arm64": {
            "url": "https://github.com/gohugoio/hugo/releases/download/v0.163.0/hugo_0.163.0_windows-arm64.zip",
            "hash": "7761762ad2b8b7f4ea3e1f05c5ecb83b0e39cd5e31f79b4380d551b9c04b83c6"
        }
    },
    "bin": "hugo.exe",
    "checkver": {
        "github": "https://github.com/gohugoio/hugo"
    },
    "autoupdate": {
        "architecture": {
            "64bit": {
                "url": "https://github.com/gohugoio/hugo/releases/download/v$version/hugo_$version_windows-amd64.zip"
            },
            "arm64": {
                "url": "https://github.com/gohugoio/hugo/releases/download/v$version/hugo_$version_windows-arm64.zip"
            }
        },
        "hash": {
            "url": "$baseurl/hugo_$version_checksums.txt"
        }
    }
}
