{
    "version": "1.30.0",
    "description": "A powerful duplicate file finder",
    "homepage": "https://codeberg.org/jbruchon/jdupes",
    "license": "MIT",
    "architecture": {
        "64bit": {
            "url": "https://codeberg.org/jbruchon/jdupes/releases/download/v1.30.0/jdupes-1.30.0-win64.zip",
            "hash": "ebbc0d403e95eb6f59f6b0dafd576d9fb8c80a7cb2447cbc14a71412d2bdec9a",
            "extract_dir": "jdupes-1.30.0-win64"
        },
        "32bit": {
            "url": "https://codeberg.org/jbruchon/jdupes/releases/download/v1.30.0/jdupes-1.30.0-win32.zip",
            "hash": "289c3abeac303d9272c31b7ee1eca705b0943981ece8a5261f0395460560b793",
            "extract_dir": "jdupes-1.30.0-win32"
        }
    },
    "bin": "jdupes.exe",
    "checkver": {
        "url": "https://codeberg.org/api/v1/repos/jbruchon/jdupes/releases/latest",
        "jsonpath": "$.tag_name",
        "regex": "v([\\d.]+)"
    },
    "autoupdate": {
        "architecture": {
            "64bit": {
                "url": "https://codeberg.org/jbruchon/jdupes/releases/download/v$version/jdupes-$version-win64.zip",
                "extract_dir": "jdupes-$version-win64"
            },
            "32bit": {
                "url": "https://codeberg.org/jbruchon/jdupes/releases/download/v$version/jdupes-$version-win32.zip",
                "extract_dir": "jdupes-$version-win32"
            }
        }
    }
}
