{
    "version": "2.542",
    "description": "An automation server which enables developers around the world to reliably build, test, and deploy their software.",
    "homepage": "https://www.jenkins.io",
    "license": "MIT",
    "suggest": {
        "Java 11": "java/openjdk11",
        "Java 17": "java/openjdk17"
    },
    "url": "https://get.jenkins.io/war/2.542/jenkins.war#/jenkins.jar",
    "hash": "b0a46c076e0bd3bfe76d6fd20f0de17316424f2b9b1528e96ae0ec16c4b19230",
    "bin": "jenkins.jar",
    "checkver": {
        "url": "https://www.jenkins.io/changelog/rss.xml",
        "xpath": "/rss/channel/item/title",
        "regex": "Jenkins ([\\d.]+)"
    },
    "autoupdate": {
        "url": "https://get.jenkins.io/war/$version/jenkins.war#/jenkins.jar",
        "hash": {
            "url": "$url.sha256"
        }
    }
}
