{
    "version": "2.72.3",
    "description": "Command line interface for Artifactory and Bintray",
    "homepage": "https://jfrog.com/getcli/",
    "license": "Apache-2.0",
    "architecture": {
        "64bit": {
            "url": "https://releases.jfrog.io/artifactory/jfrog-cli/v2/2.72.3/jfrog-cli-windows-amd64/jfrog.exe",
            "hash": "73ba84a685187a41bc4b8d708ed9b05dd94d3e913439830e316c2d85862d0c7a"
        }
    },
    "bin": "jfrog.exe",
    "checkver": {
        "url": "https://github.com/jfrog/jfrog-cli/releases",
        "regex": "tag/v(2\\.[\\d.]+)"
    },
    "autoupdate": {
        "architecture": {
            "64bit": {
                "url": "https://releases.jfrog.io/artifactory/jfrog-cli/v$majorVersion/$version/jfrog-cli-windows-amd64/jfrog.exe"
            }
        },
        "hash": {
            "url": "$url.sha256"
        }
    }
}
