{
    "version": "3.0.3",
    "description": "Scans K8s clusters, YAML files, and HELM charts, and detect misconfigurations and software vulnerabilities at early stages of the CI/CD pipeline and provides a risk score instantly and risk trends over time.",
    "homepage": "https://github.com/kubescape/kubescape/",
    "license": "Apache-2.0",
    "architecture": {
        "64bit": {
            "url": "https://github.com/kubescape/kubescape/releases/download/v3.0.3/kubescape.exe",
            "hash": "8bee67f8ac13d638de02de1951fb1a04ef0f49314aaa3863bb62b21879c4a605"
        }
    },
    "bin": "kubescape.exe",
    "checkver": "github",
    "autoupdate": {
        "architecture": {
            "64bit": {
                "url": "https://github.com/kubescape/kubescape/releases/download/v$version/kubescape.exe"
            }
        }
    }
}
