{
    "version": "1.13.1",
    "description": "Kyverno CLI to manage Kubernetes policies",
    "homepage": "https://kyverno.io/docs/kyverno-cli/",
    "license": "Apache-2.0",
    "architecture": {
        "64bit": {
            "url": "https://github.com/kyverno/kyverno/releases/download/v1.13.1/kyverno-cli_v1.13.1_windows_x86_64.zip",
            "hash": "6cb4224fa29b16bf29aa476e4950c98419cef8cb6e1456b4fd77689a0d260211"
        }
    },
    "bin": "kyverno.exe",
    "checkver": {
        "github": "https://github.com/kyverno/kyverno"
    },
    "autoupdate": {
        "architecture": {
            "64bit": {
                "url": "https://github.com/kyverno/kyverno/releases/download/v$version/kyverno-cli_v$version_windows_x86_64.zip"
            }
        },
        "hash": {
            "url": "$baseurl/checksums.txt"
        }
    }
}
