{
    "version": "1.17.0",
    "homepage": "https://dlang.org/",
    "description": "LDC is LLVM based D-language compiler",
    "license": {
        "identifier": "BSD-3-Clause,BSL-1.0,NCSA,MIT,GPL-2.0-or-later",
        "url": "https://github.com/ldc-developers/ldc/blob/master/LICENSE"
    },
    "architecture": {
        "64bit": {
            "url": "https://github.com/ldc-developers/ldc/releases/download/v1.17.0/ldc2-1.17.0-windows-x64.7z",
            "extract_dir": "ldc2-1.17.0-windows-x64",
            "hash": "a36875ca90287c37e4dec63b98b8bc178aa1f3dcc1982114656c8fe576f1ee47"
        },
        "32bit": {
            "url": "https://github.com/ldc-developers/ldc/releases/download/v1.17.0/ldc2-1.17.0-windows-x86.7z",
            "extract_dir": "ldc2-1.17.0-windows-x86",
            "hash": "96e7ab01119bef6e737aefeb0798ad4131e22a3bc3e95a98df7decaf200da27d"
        }
    },
    "env_add_path": "bin",
    "checkver": {
        "github": "https://github.com/ldc-developers/ldc/"
    },
    "autoupdate": {
        "architecture": {
            "64bit": {
                "url": "https://github.com/ldc-developers/ldc/releases/download/v$version/ldc2-$version-windows-x64.7z",
                "extract_dir": "ldc2-$version-windows-x64"
            },
            "32bit": {
                "url": "https://github.com/ldc-developers/ldc/releases/download/v$version/ldc2-$version-windows-x86.7z",
                "extract_dir": "ldc2-$version-windows-x86"
            }
        }
    }
}
