{
    "version": "0.16.2",
    "description": "Generate an OCI compliant image based off app source.",
    "homepage": "https://github.com/railwayapp/nixpacks",
    "license": "MIT",
    "suggest": {
        "vcredist": "extras/vcredist2022"
    },
    "architecture": {
        "64bit": {
            "url": "https://github.com/railwayapp/nixpacks/releases/download/v0.16.2/nixpacks-v0.16.2-x86_64-pc-windows-msvc.zip",
            "hash": "8325dc4dfea786c8e3f90101bf02ab69bcb2edf84fff67f65f80b404038fc8a8",
            "extract_dir": "nixpacks-v0.16.2-x86_64-pc-windows-msvc"
        },
        "32bit": {
            "url": "https://github.com/railwayapp/nixpacks/releases/download/v0.16.2/nixpacks-v0.16.2-i686-pc-windows-msvc.zip",
            "hash": "7b340385c0df93d8cd182a9fafa47c25b46223f8de39d6928d58756538ae6661",
            "extract_dir": "nixpacks-v0.16.2-i686-pc-windows-msvc"
        }
    },
    "bin": "nixpacks.exe",
    "checkver": "github",
    "autoupdate": {
        "architecture": {
            "64bit": {
                "url": "https://github.com/railwayapp/nixpacks/releases/download/v$version/nixpacks-v$version-x86_64-pc-windows-msvc.zip",
                "extract_dir": "nixpacks-v$version-x86_64-pc-windows-msvc"
            },
            "32bit": {
                "url": "https://github.com/railwayapp/nixpacks/releases/download/v$version/nixpacks-v$version-i686-pc-windows-msvc.zip",
                "extract_dir": "nixpacks-v$version-i686-pc-windows-msvc"
            }
        }
    }
}
