{
    "version": "0.1.410",
    "description": "Collection of tools for analyzing open source packages.",
    "homepage": "https://github.com/microsoft/OSSGadget",
    "license": "MIT",
    "architecture": {
        "64bit": {
            "url": "https://github.com/microsoft/OSSGadget/releases/download/v0.1.410/OSSGadget_win_0.1.410.zip",
            "hash": "8163ff10922879a9fa082351d5bc6e9cbfce3352baec7b861fc0144497e1d33d",
            "extract_dir": "OSSGadget_win_0.1.410"
        }
    },
    "bin": [
        "oss-characteristic.exe",
        "oss-defog.exe",
        "oss-detect-backdoor.exe",
        "oss-detect-cryptography.exe",
        "oss-diff.exe",
        "oss-download.exe",
        "oss-find-domain-squats.exe",
        "oss-find-source.exe",
        "oss-find-squats.exe",
        "oss-health.exe",
        "oss-metadata.exe",
        "oss-risk-calculator.exe"
    ],
    "checkver": "github",
    "autoupdate": {
        "architecture": {
            "64bit": {
                "url": "https://github.com/microsoft/OSSGadget/releases/download/v$version/OSSGadget_win_$version.zip",
                "hash": {
                    "url": "https://github.com/microsoft/OSSGadget/releases/download/v$version/HASHES.txt"
                },
                "extract_dir": "OSSGadget_win_$version"
            }
        }
    }
}
