{
    "version": "1.2.0",
    "description": "An open source CDC command-line tool and library that offers Postgres replication support with DDL changes to any provided target.",
    "homepage": "https://xata.io/documentation/opensource/pgstream/overview",
    "license": "Apache-2.0",
    "architecture": {
        "64bit": {
            "url": "https://github.com/xataio/pgstream/releases/download/v1.2.0/pgstream.win.amd64.exe#/pgstream.exe",
            "hash": "99531b61fe1b5ca8776a22fc6a1f734042294009e44e55159292ea1d67115588"
        }
    },
    "bin": "pgstream.exe",
    "checkver": {
        "github": "https://github.com/xataio/pgstream"
    },
    "autoupdate": {
        "architecture": {
            "64bit": {
                "url": "https://github.com/xataio/pgstream/releases/download/v$version/pgstream.win.amd64.exe#/pgstream.exe"
            }
        },
        "hash": {
            "url": "$baseurl/pgstream_$version_checksums.txt"
        }
    }
}
