{
    "version": "0.52.0",
    "description": "Package management made easy",
    "homepage": "https://pixi.sh",
    "license": "BSD-3-Clause",
    "architecture": {
        "64bit": {
            "url": "https://github.com/prefix-dev/pixi/releases/download/v0.52.0/pixi-x86_64-pc-windows-msvc.zip",
            "hash": "0b04bc61c0de0dfb6c9925ac4104403266ea143d55ff59457dc508ba012118cf"
        },
        "arm64": {
            "url": "https://github.com/prefix-dev/pixi/releases/download/v0.52.0/pixi-aarch64-pc-windows-msvc.zip",
            "hash": "ce760a81739592d59f984fe189dacd9f6640a0dd00ef651ff61e0a7f1fd3919e"
        }
    },
    "bin": "pixi.exe",
    "checkver": {
        "github": "https://github.com/prefix-dev/pixi"
    },
    "autoupdate": {
        "architecture": {
            "64bit": {
                "url": "https://github.com/prefix-dev/pixi/releases/download/v$version/pixi-x86_64-pc-windows-msvc.zip",
                "hash": {
                    "url": "$url.sha256"
                }
            },
            "arm64": {
                "url": "https://github.com/prefix-dev/pixi/releases/download/v$version/pixi-aarch64-pc-windows-msvc.zip",
                "hash": {
                    "url": "$url.sha256"
                }
            }
        }
    }
}
