{
    "version": "1.2.1",
    "description": "gRPC javascript code generator plugin for Web Clients",
    "homepage": "https://grpc.io",
    "license": "Apache-2.0",
    "architecture": {
        "64bit": {
            "url": "https://github.com/grpc/grpc-web/releases/download/1.2.1/protoc-gen-grpc-web-1.2.1-windows-x86_64.exe#/protoc-gen-grpc-web.exe",
            "hash": "5886b4c9886dfdbfd1c7c2f26a15c396c6662b9f1acf9b6d8efbd490bc3736db"
        }
    },
    "bin": "protoc-gen-grpc-web.exe",
    "checkver": {
        "github": "https://github.com/grpc/grpc-web"
    },
    "autoupdate": {
        "architecture": {
            "64bit": {
                "url": "https://github.com/grpc/grpc-web/releases/download/$version/protoc-gen-grpc-web-$version-windows-x86_64.exe#/protoc-gen-grpc-web.exe"
            }
        },
        "hash": {
            "url": "$url.sha256"
        }
    }
}
