{
    "version": "9.1.0",
    "description": "A command line CSV data-wrangling toolkit",
    "homepage": "https://qsv.dathere.com",
    "license": "Unlicense|MIT",
    "notes": "Only the full featured \"qsv\" build is included",
    "architecture": {
        "64bit": {
            "url": "https://github.com/dathere/qsv/releases/download/9.1.0/qsv-9.1.0-x86_64-pc-windows-msvc.zip",
            "hash": "12acf84e69229ba38f9448df527f88a0979f4582cea44c910aa8382eb3bb694d"
        }
    },
    "pre_install": "Get-ChildItem -Path \"$dir\" -Exclude README,qsv.exe | Remove-Item -Force",
    "bin": "qsv.exe",
    "checkver": {
        "github": "https://github.com/dathere/qsv"
    },
    "autoupdate": {
        "architecture": {
            "64bit": {
                "url": "https://github.com/dathere/qsv/releases/download/$version/qsv-$version-x86_64-pc-windows-msvc.zip"
            }
        }
    }
}
