{
    "homepage": "https://github.com/sass/dart-sass",
    "description": "The reference implementation of Sass, written in Dart.",
    "version": "1.24.4",
    "license": "MIT",
    "architecture": {
        "64bit": {
            "url": "https://github.com/sass/dart-sass/releases/download/1.24.4/dart-sass-1.24.4-windows-x64.zip",
            "hash": "f4251982c68322ca998734f821aa8dc3971a3bed71e096ff16959300191c34ce"
        },
        "32bit": {
            "url": "https://github.com/sass/dart-sass/releases/download/1.24.4/dart-sass-1.24.4-windows-ia32.zip",
            "hash": "b19704d52538b21ed21939ba8aab76fff22f738e5e42378a37dcd85806441d69"
        }
    },
    "extract_dir": "dart-sass",
    "bin": [
        [
            "sass.bat",
            "sass"
        ]
    ],
    "checkver": {
        "url": "https://github.com/sass/dart-sass/releases/latest",
        "re": "/releases/tag/(?:v)?([\\d\\w.-]+)"
    },
    "autoupdate": {
        "architecture": {
            "64bit": {
                "url": "https://github.com/sass/dart-sass/releases/download/$version/dart-sass-$version-windows-x64.zip"
            },
            "32bit": {
                "url": "https://github.com/sass/dart-sass/releases/download/$version/dart-sass-$version-windows-ia32.zip"
            }
        }
    }
}
