{
    "version": "2.42.3",
    "description": "Connect to the Sentry API and manage projects related data.",
    "homepage": "https://docs.sentry.io/cli/",
    "license": "BSD-3-Clause",
    "architecture": {
        "64bit": {
            "url": "https://github.com/getsentry/sentry-cli/releases/download/2.42.3/sentry-cli-Windows-x86_64.exe#/sentry.exe",
            "hash": "a2161480f821695bfd4edee67d84d3e4fa764336fcc5d42d13a55cbe7ab7bbd5"
        },
        "32bit": {
            "url": "https://github.com/getsentry/sentry-cli/releases/download/2.42.3/sentry-cli-Windows-i686.exe#/sentry.exe",
            "hash": "39c13236eb7a8c24c6431264b9f60e68f5fe2b8f9840913b61eda52f33e22e25"
        }
    },
    "bin": [
        "sentry.exe",
        [
            "sentry.exe",
            "sentry-cli"
        ]
    ],
    "checkver": {
        "github": "https://github.com/getsentry/sentry-cli"
    },
    "autoupdate": {
        "architecture": {
            "64bit": {
                "url": "https://github.com/getsentry/sentry-cli/releases/download/$version/sentry-cli-Windows-x86_64.exe#/sentry.exe"
            },
            "32bit": {
                "url": "https://github.com/getsentry/sentry-cli/releases/download/$version/sentry-cli-Windows-i686.exe#/sentry.exe"
            }
        }
    }
}
