{
    "version": "4.4.4",
    "description": "Privileged access management for cloud-native infrastructure.",
    "homepage": "https://gravitational.com/teleport",
    "license": "Apache-2.0",
    "architecture": {
        "64bit": {
            "url": "https://get.gravitational.com/teleport-v4.4.4-windows-amd64-bin.zip",
            "hash": "baec40b4b32b18859bbf40a6a5b2b15ee77c3dc0339b28cb5770c9788a185775"
        }
    },
    "extract_dir": "teleport",
    "bin": "tsh.exe",
    "checkver": {
        "github": "https://github.com/gravitational/teleport"
    },
    "autoupdate": {
        "architecture": {
            "64bit": {
                "url": "https://get.gravitational.com/teleport-v$version-windows-amd64-bin.zip"
            }
        },
        "hash": {
            "url": "$url.sha256"
        }
    }
}
