{
    "version": "0.14.9",
    "description": "Create and manage infrastructure as code using simple declarative configuration files.",
    "homepage": "https://www.terraform.io",
    "license": "MPL-2.0",
    "architecture": {
        "64bit": {
            "url": "https://releases.hashicorp.com/terraform/0.14.9/terraform_0.14.9_windows_amd64.zip",
            "hash": "8814aacbab1e15c42a1f9f978401500ef8c33e4075f8a29a74e3a67a1a535e26",
            "pre_install": "ensure \"$env:APPDATA\\terraform.d\\plugins\\windows_amd64\" | Out-Null"
        },
        "32bit": {
            "url": "https://releases.hashicorp.com/terraform/0.14.9/terraform_0.14.9_windows_386.zip",
            "hash": "66b508be761319aab846cf9bce3e7f92ebe603b0c3cdda06d1c4d69561bd69f2",
            "pre_install": "ensure \"$env:APPDATA\\terraform.d\\plugins\\windows_386\" | Out-Null"
        }
    },
    "bin": "terraform.exe",
    "checkver": {
        "url": "https://releases.hashicorp.com/terraform/",
        "regex": "terraform_([\\d.]+)</a>"
    },
    "autoupdate": {
        "architecture": {
            "64bit": {
                "url": "https://releases.hashicorp.com/terraform/$version/terraform_$version_windows_amd64.zip"
            },
            "32bit": {
                "url": "https://releases.hashicorp.com/terraform/$version/terraform_$version_windows_386.zip"
            }
        },
        "hash": {
            "url": "$baseurl/terraform_$version_SHA256SUMS"
        }
    }
}
