{
    "version": "0.64.1",
    "description": "Thin wrapper for Terraform that provides extra tools for keeping Terraform configurations DRY, working with multiple Terraform modules, and managing remote state.",
    "homepage": "https://github.com/gruntwork-io/terragrunt",
    "license": "MIT",
    "architecture": {
        "64bit": {
            "url": "https://github.com/gruntwork-io/terragrunt/releases/download/v0.64.1/terragrunt_windows_amd64.exe#/terragrunt.exe",
            "hash": "2353970b2f4d276e02bdf970fc2e20cd16a27edc853c8cc804f7d6604460b021"
        },
        "32bit": {
            "url": "https://github.com/gruntwork-io/terragrunt/releases/download/v0.64.1/terragrunt_windows_386.exe#/terragrunt.exe",
            "hash": "df12a35592e1698e930357ffe3775971418b224ff5d916627b45d84df83809f7"
        }
    },
    "bin": "terragrunt.exe",
    "checkver": "github",
    "autoupdate": {
        "architecture": {
            "64bit": {
                "url": "https://github.com/gruntwork-io/terragrunt/releases/download/v$version/terragrunt_windows_amd64.exe#/terragrunt.exe"
            },
            "32bit": {
                "url": "https://github.com/gruntwork-io/terragrunt/releases/download/v$version/terragrunt_windows_386.exe#/terragrunt.exe"
            }
        },
        "hash": {
            "url": "$baseurl/SHA256SUMS"
        }
    }
}
