{
    "version": "1.15.4",
    "description": "A static analysis security scanner for Terraform code",
    "homepage": "https://tfsec.dev",
    "license": "MIT",
    "architecture": {
        "64bit": {
            "url": "https://github.com/aquasecurity/tfsec/releases/download/v1.15.4/tfsec-windows-amd64.exe#/tfsec.exe",
            "hash": "59435234dee9a907a91cd30272e56e42e10d6b7844bc60b7a91824afd7e62b7d"
        }
    },
    "bin": "tfsec.exe",
    "checkver": {
        "github": "https://github.com/aquasecurity/tfsec"
    },
    "autoupdate": {
        "architecture": {
            "64bit": {
                "url": "https://github.com/aquasecurity/tfsec/releases/download/v$version/tfsec-windows-amd64.exe#/tfsec.exe"
            }
        },
        "hash": {
            "url": "$baseurl/tfsec_checksums.txt"
        }
    }
}
