{
    "version": "3.93.5",
    "description": "Find leaked credentials",
    "homepage": "https://github.com/trufflesecurity/trufflehog",
    "license": "AGPL-3.0-only",
    "architecture": {
        "64bit": {
            "url": "https://github.com/trufflesecurity/trufflehog/releases/download/v3.93.5/trufflehog_3.93.5_windows_amd64.tar.gz",
            "hash": "4ee1044a9a0e06639149ed8abb54e596b146cf744b548e7c654960ca645d45a8"
        }
    },
    "bin": "trufflehog.exe",
    "checkver": "github",
    "autoupdate": {
        "architecture": {
            "64bit": {
                "url": "https://github.com/trufflesecurity/trufflehog/releases/download/v$version/trufflehog_$version_windows_amd64.tar.gz"
            }
        },
        "hash": {
            "url": "$baseurl/trufflehog_$version_checksums.txt"
        }
    }
}
