{
    "version": "2.3.1",
    "description": "Standalone, simple NFS Server for Windows",
    "homepage": "https://github.com/winnfsd/winnfsd",
    "license": "GPL-2.0-only",
    "url": "https://github.com/winnfsd/winnfsd/releases/download/2.3.1/WinNFSd.exe",
    "hash": "bd1d7dbfdffb2cbc21e2c0f30b32d87735c14706214cf8e2811a2eef8fb87fc0",
    "bin": "WinNFSd.exe",
    "checkver": "github",
    "autoupdate": {
        "url": "https://github.com/winnfsd/winnfsd/releases/download/$version/WinNFSd.exe"
    }
}
