{
    "version": "1.4.14",
    "description": "The official command-line interface for Xata, an open source Postgres platform.",
    "homepage": "https://xata.io/docs/cli",
    "license": "Apache-2.0",
    "architecture": {
        "64bit": {
            "url": "https://xata-cli-versions.s3.amazonaws.com/versions/1.4.14-latest/xata-windows-x64.exe#/xata.exe",
            "hash": "dec03185d710a286e6c973a3b4b77424636afee1f8346a5f903d23dc7731ad0d"
        }
    },
    "bin": "xata.exe",
    "checkver": {
        "url": "https://xata-cli-versions.s3.amazonaws.com/channels/latest/manifest.json",
        "jsonpath": "$.version"
    },
    "autoupdate": {
        "architecture": {
            "64bit": {
                "url": "https://xata-cli-versions.s3.amazonaws.com/versions/$version-latest/xata-windows-x64.exe#/xata.exe"
            }
        },
        "hash": {
            "url": "$baseurl/manifest.json",
            "jsonpath": "$..[?(@.url == '$url')].sha256sum"
        }
    }
}
